bloc/__init__.py
bloc/client.py
bloc/server.py
bloc/tap.py
bloc/utils.py
bloc-0.1.2.dist-info/DESCRIPTION.rst
bloc-0.1.2.dist-info/METADATA
bloc-0.1.2.dist-info/RECORD
bloc-0.1.2.dist-info/WHEEL
bloc-0.1.2.dist-info/metadata.json
bloc-0.1.2.dist-info/top_level.txt
twisted/plugins/bloc.py
