Metadata-Version: 2.0
Name: bloc
Version: 0.1.2
Summary: Single-master group membership framework
Home-page: https://github.com/manishtomar/bloc
Author: Manish Tomar
Author-email: manishtomar.public@gmail.com
License: MIT
Keywords: group membership distributed systems
Platform: UNKNOWN
Classifier: Development Status :: 3 - Alpha
Classifier: Intended Audience :: Developers
Classifier: License :: OSI Approved :: MIT License
Classifier: Natural Language :: English
Classifier: Programming Language :: Python :: 2
Classifier: Programming Language :: Python :: 2.7
Classifier: Programming Language :: Python :: 3
Classifier: Topic :: Internet :: WWW/HTTP
Requires-Dist: klein (>=15.0.0)
Requires-Dist: treq (>=15.1.0)
Requires-Dist: twisted (>=16.5.0)
